chinese_synonym_word/__init__.py
chinese_synonym_word/chinese_synonym_word.py
chinese_synonym_word/model/__init__.py
chinese_synonym_word/model/test.model
chinese_synonym_word-0.1.6.dist-info/METADATA
chinese_synonym_word-0.1.6.dist-info/WHEEL
chinese_synonym_word-0.1.6.dist-info/top_level.txt
chinese_synonym_word-0.1.6.dist-info/RECORD
