Metadata-Version: 2.1
Name: chinese-synonym-word
Version: 0.1.6
Summary: chinese-synonym-word
Home-page: https://github.com/Suncicie/chinese-synonym-word
Author: sunsi
Author-email: 449860952@qq.com
License: MIT
Platform: UNKNOWN
Classifier: Programming Language :: Python :: 3
Classifier: License :: OSI Approved :: MIT License
Classifier: Operating System :: OS Independent
